agdiff/__init__.py
agdiff/main.py
agdiff-0.0.2.dist-info/METADATA
agdiff-0.0.2.dist-info/WHEEL
agdiff-0.0.2.dist-info/entry_points.txt
agdiff-0.0.2.dist-info/licenses/LICENSE
agdiff-0.0.2.dist-info/RECORD
