Metadata-Version: 2.3
Name: agdiff
Version: 0.0.2
Summary: A tool for doing diffs over an air gap
Project-URL: Homepage, https://github.com/scottbelden/agdiff
Project-URL: Issues, https://github.com/scottbelden/agdiff/issues
Author-email: Scott Belden <scottabelden@gmail.com>
License-File: LICENSE
Classifier: License :: OSI Approved :: MIT License
Classifier: Operating System :: OS Independent
Classifier: Programming Language :: Python :: 3
Requires-Python: >=3.8
Requires-Dist: typer[all]
Provides-Extra: test
Requires-Dist: build; extra == 'test'
Requires-Dist: pyright; extra == 'test'
Requires-Dist: pytest; extra == 'test'
Requires-Dist: pytest-cov; extra == 'test'
Requires-Dist: ruff; extra == 'test'
